LICENSE.txt
README.md
setup.cfg
setup.py
pyrtmp/__init__.py
pyrtmp/flv.py
pyrtmp/rtmp.py
pyrtmp/session_manager.py
pyrtmp.egg-info/PKG-INFO
pyrtmp.egg-info/SOURCES.txt
pyrtmp.egg-info/dependency_links.txt
pyrtmp.egg-info/requires.txt
pyrtmp.egg-info/top_level.txt
pyrtmp/amf/__init__.py
pyrtmp/amf/serializers.py
pyrtmp/amf/types.py
pyrtmp/messages/__init__.py
pyrtmp/messages/aggregate.py
pyrtmp/messages/audio.py
pyrtmp/messages/command.py
pyrtmp/messages/data.py
pyrtmp/messages/factory.py
pyrtmp/messages/handshake.py
pyrtmp/messages/protocol_control.py
pyrtmp/messages/shared_object.py
pyrtmp/messages/user_control.py
pyrtmp/messages/video.py
tests/__init__.py
tests/test_demo_ffmpeg.py
tests/test_demo_flvdump.py
tests/test_demo_rtmpt.py
tests/test_pyrtmp.py