Metadata-Version: 2.1
Name: pyrtmp
Version: 0.3.0
Summary: PyRTMP: Pure Python RTMP server
Home-page: https://github.com/Eittipat/pyrtmp.git
Download-URL: https://github.com/Eittipat/pyrtmp/releases/tag/v0.3.0
Author: Eittipat.K
Author-email: iammop@gmail.com
License: MIT
Keywords: RTMP,RTMPT,asyncio
Classifier: Development Status :: 5 - Production/Stable
Classifier: Intended Audience :: Developers
Classifier: Topic :: Software Development :: Build Tools
Classifier: License :: OSI Approved :: MIT License
Classifier: Programming Language :: Python :: 3
Requires-Python: >=3.10
License-File: LICENSE.txt
Requires-Dist: bitstring>=4
